agora_realtime_ai_api/__init__.py
agora_realtime_ai_api/logger.py
agora_realtime_ai_api/rtc.py
agora_realtime_ai_api/token_builder/AccessToken2.py
agora_realtime_ai_api/token_builder/Packer.py
agora_realtime_ai_api/token_builder/RtcTokenBuilder2.py
agora_realtime_ai_api/token_builder/__init__.py
agora_realtime_ai_api/token_builder/realtimekit_token_builder.py
agora_realtime_ai_api-1.1.0.dist-info/LICENSE
agora_realtime_ai_api-1.1.0.dist-info/METADATA
agora_realtime_ai_api-1.1.0.dist-info/WHEEL
agora_realtime_ai_api-1.1.0.dist-info/top_level.txt
agora_realtime_ai_api-1.1.0.dist-info/RECORD
